pygremlinbox_mpl_1_1/__init__.py
pygremlinbox_mpl_1_1-1.4.0.dist-info/licenses/LICENCE
pygremlinbox_mpl_1_1-1.4.0.dist-info/METADATA
pygremlinbox_mpl_1_1-1.4.0.dist-info/WHEEL
pygremlinbox_mpl_1_1-1.4.0.dist-info/top_level.txt
pygremlinbox_mpl_1_1-1.4.0.dist-info/RECORD
