Metadata-Version: 2.4
Name: pygremlinbox-mpl-1-1
Version: 1.4.0
Summary: PyGremlinBox MPL-1.1 - Supply chain security testing module with MPL-1.1 licence
Author-email: Supply Chain Security Tester <simon@sigre.xyz>
Maintainer-email: Supply Chain Security Tester <simon@sigre.xyz>
License: MPL-1.1
Project-URL: Homepage, https://github.com/gocortexio/pygremlinbox
Project-URL: Repository, https://github.com/gocortexio/pygremlinbox.git
Project-URL: Issues, https://github.com/gocortexio/pygremlinbox/issues
Keywords: security,supply-chain,testing,licence
Classifier: Development Status :: 4 - Beta
Classifier: Intended Audience :: Developers
Classifier: Operating System :: OS Independent
Classifier: Programming Language :: Python :: 3
Classifier: Programming Language :: Python :: 3.8
Classifier: Programming Language :: Python :: 3.9
Classifier: Programming Language :: Python :: 3.10
Classifier: Programming Language :: Python :: 3.11
Classifier: Programming Language :: Python :: 3.12
Classifier: Topic :: Security
Classifier: Topic :: Software Development :: Testing
Requires-Python: >=3.8
License-File: LICENCE
Dynamic: license-file
